<?xml version="1.0" encoding="ISO-8859-1"?>
<metier>
<MET_LIBELLE_METIER label="Nom du métier" store="yes">tailleur/euse et couturier/ère</MET_LIBELLE_METIER>
<MET_CENTRE_INTERET label="Descripteur thesaurus Centres d'intérêt">exercer un travail manuel/exercer un métier artistique ou créatif/fabriquer, construire/travailler un matériau</MET_CENTRE_INTERET>
<MET_CATEGORIE_SOCIO_PRO label="Descripteur thesaurus Statuts">artisan/salarié</MET_CATEGORIE_SOCIO_PRO>
<MET_DOMAINE label="Descripteur thesaurus Fonctions">fonction fabrication artisanale/fonction vente</MET_DOMAINE>
<MET_SECTEUR_ACTIVITE label="Descripteur thesaurus Secteurs d'activité">secteur textile habillement/secteur artisanat d'art</MET_SECTEUR_ACTIVITE>
<MET_DISCIPLINE label="Descripteur thesaurus Disciplines">art de la mode/vêtement sur mesure/cuirs et peaux/chemiserie lingerie corseterie/broderie dentelle passementerie/fourrure pelleterie/artisanat d'art/fabrication habillement</MET_DISCIPLINE>
<MET_GFE label="Descripteur thesaurus GFE">GFE textile habillement cuir/tailleur couturier</MET_GFE>
<lien_onisep>http://www.onisep.fr/http/redirection/metier/identifiant/10396</lien_onisep>
<ROME Level="1B" csRelFld="10396">
<FAMILLE_PROF_ROME Level="1B1">
<record Level="1B1" csKeyFld="61" csRelFld="61">
<CSLABELFLD label="">B1803</CSLABELFLD>
<FAM_FAMROM_ID label="Famille">Tissu et cuirs</FAM_FAMROM_ID>
<FAMROM_CODE_ROME label="Code ROME">B1803</FAMROM_CODE_ROME>
<FAMROM_LIBELLE label="Libellé">Réalisation de vêtements sur mesure ou en petite série</FAMROM_LIBELLE>
</record>
</FAMILLE_PROF_ROME>
</ROME>
<Métiers_associés Level="1C" csRelFld="10396">
<METIER_CONNEXE Level="1C1">
<record Level="1C1" csKeyFld="1498" csRelFld="1498">
<CSLABELFLD label="">apiéceur / apiéceuse</CSLABELFLD>
<MET_ID label="Identifiant">10396</MET_ID>
<METCONN_CATEGORIE_SOCIO_PRO label="Descripteur thesaurus Statuts"/>
<METCONN_CENTRE_INTERET label="Descripteur thesaurus Centres d'intérêt"/>
<METCONN_DATE_CREATION label="Créé le">20/10/2014</METCONN_DATE_CREATION>
<METCONN_DATE_MODIFICATION label="Modifié le"/>
<METCONN_DISCIPLINE label="Descripteur thesaurus Disciplines"/>
<METCONN_DOMAINE label="Descripteur thesaurus Fonctions"/>
<METCONN_GFE label="Descripteur thesaurus GFE"/>
<METCONN_ID label="ID">1498</METCONN_ID>
<METCONN_LIBELLE_METIER label="Nom du métier">apiéceur/euse</METCONN_LIBELLE_METIER>
<METCONN_SECTEUR_ACTIVITE label="Descripteur thesaurus Secteurs d'activité"/>
<METCONN_USER_MODIFICATION label="Utilisateur">edi</METCONN_USER_MODIFICATION>
<Thesaurus Level="1C1A" csRelFld="1498">
<CSTM_T Level="1C1A1"/>
</Thesaurus>
</record>
<record Level="1C1" csKeyFld="1499" csRelFld="1499">
<CSLABELFLD label="">boutonniériste</CSLABELFLD>
<MET_ID label="Identifiant">10396</MET_ID>
<METCONN_CATEGORIE_SOCIO_PRO label="Descripteur thesaurus Statuts"/>
<METCONN_CENTRE_INTERET label="Descripteur thesaurus Centres d'intérêt"/>
<METCONN_DATE_CREATION label="Créé le">20/10/2014</METCONN_DATE_CREATION>
<METCONN_DATE_MODIFICATION label="Modifié le"/>
<METCONN_DISCIPLINE label="Descripteur thesaurus Disciplines"/>
<METCONN_DOMAINE label="Descripteur thesaurus Fonctions"/>
<METCONN_GFE label="Descripteur thesaurus GFE"/>
<METCONN_ID label="ID">1499</METCONN_ID>
<METCONN_LIBELLE_METIER label="Nom du métier">boutonniériste</METCONN_LIBELLE_METIER>
<METCONN_SECTEUR_ACTIVITE label="Descripteur thesaurus Secteurs d'activité"/>
<METCONN_USER_MODIFICATION label="Utilisateur">edi</METCONN_USER_MODIFICATION>
<Thesaurus Level="1C1A" csRelFld="1499">
<CSTM_T Level="1C1A1"/>
</Thesaurus>
</record>
<record Level="1C1" csKeyFld="1500" csRelFld="1500">
<CSLABELFLD label="">corsetier / corsetière</CSLABELFLD>
<MET_ID label="Identifiant">10396</MET_ID>
<METCONN_CATEGORIE_SOCIO_PRO label="Descripteur thesaurus Statuts"/>
<METCONN_CENTRE_INTERET label="Descripteur thesaurus Centres d'intérêt"/>
<METCONN_DATE_CREATION label="Créé le">20/10/2014</METCONN_DATE_CREATION>
<METCONN_DATE_MODIFICATION label="Modifié le"/>
<METCONN_DISCIPLINE label="Descripteur thesaurus Disciplines"/>
<METCONN_DOMAINE label="Descripteur thesaurus Fonctions"/>
<METCONN_GFE label="Descripteur thesaurus GFE"/>
<METCONN_ID label="ID">1500</METCONN_ID>
<METCONN_LIBELLE_METIER label="Nom du métier">corsetier/ère</METCONN_LIBELLE_METIER>
<METCONN_SECTEUR_ACTIVITE label="Descripteur thesaurus Secteurs d'activité"/>
<METCONN_USER_MODIFICATION label="Utilisateur">edi</METCONN_USER_MODIFICATION>
<Thesaurus Level="1C1A" csRelFld="1500">
<CSTM_T Level="1C1A1"/>
</Thesaurus>
</record>
<record Level="1C1" csKeyFld="1501" csRelFld="1501">
<CSLABELFLD label="">coupeur-tailleur / coupeuse-tailleuse</CSLABELFLD>
<MET_ID label="Identifiant">10396</MET_ID>
<METCONN_CATEGORIE_SOCIO_PRO label="Descripteur thesaurus Statuts"/>
<METCONN_CENTRE_INTERET label="Descripteur thesaurus Centres d'intérêt"/>
<METCONN_DATE_CREATION label="Créé le">20/10/2014</METCONN_DATE_CREATION>
<METCONN_DATE_MODIFICATION label="Modifié le"/>
<METCONN_DISCIPLINE label="Descripteur thesaurus Disciplines"/>
<METCONN_DOMAINE label="Descripteur thesaurus Fonctions"/>
<METCONN_GFE label="Descripteur thesaurus GFE"/>
<METCONN_ID label="ID">1501</METCONN_ID>
<METCONN_LIBELLE_METIER label="Nom du métier">coupeur/euse-tailleur/euse</METCONN_LIBELLE_METIER>
<METCONN_SECTEUR_ACTIVITE label="Descripteur thesaurus Secteurs d'activité"/>
<METCONN_USER_MODIFICATION label="Utilisateur">edi</METCONN_USER_MODIFICATION>
<Thesaurus Level="1C1A" csRelFld="1501">
<CSTM_T Level="1C1A1"/>
</Thesaurus>
</record>
<record Level="1C1" csKeyFld="1502" csRelFld="1502">
<CSLABELFLD label="">culottier / culottière</CSLABELFLD>
<MET_ID label="Identifiant">10396</MET_ID>
<METCONN_CATEGORIE_SOCIO_PRO label="Descripteur thesaurus Statuts"/>
<METCONN_CENTRE_INTERET label="Descripteur thesaurus Centres d'intérêt"/>
<METCONN_DATE_CREATION label="Créé le">20/10/2014</METCONN_DATE_CREATION>
<METCONN_DATE_MODIFICATION label="Modifié le"/>
<METCONN_DISCIPLINE label="Descripteur thesaurus Disciplines"/>
<METCONN_DOMAINE label="Descripteur thesaurus Fonctions"/>
<METCONN_GFE label="Descripteur thesaurus GFE"/>
<METCONN_ID label="ID">1502</METCONN_ID>
<METCONN_LIBELLE_METIER label="Nom du métier">culottier/ère</METCONN_LIBELLE_METIER>
<METCONN_SECTEUR_ACTIVITE label="Descripteur thesaurus Secteurs d'activité"/>
<METCONN_USER_MODIFICATION label="Utilisateur">edi</METCONN_USER_MODIFICATION>
<Thesaurus Level="1C1A" csRelFld="1502">
<CSTM_T Level="1C1A1"/>
</Thesaurus>
</record>
<record Level="1C1" csKeyFld="1503" csRelFld="1503">
<CSLABELFLD label="">giletier / giletière</CSLABELFLD>
<MET_ID label="Identifiant">10396</MET_ID>
<METCONN_CATEGORIE_SOCIO_PRO label="Descripteur thesaurus Statuts"/>
<METCONN_CENTRE_INTERET label="Descripteur thesaurus Centres d'intérêt"/>
<METCONN_DATE_CREATION label="Créé le">20/10/2014</METCONN_DATE_CREATION>
<METCONN_DATE_MODIFICATION label="Modifié le"/>
<METCONN_DISCIPLINE label="Descripteur thesaurus Disciplines"/>
<METCONN_DOMAINE label="Descripteur thesaurus Fonctions"/>
<METCONN_GFE label="Descripteur thesaurus GFE"/>
<METCONN_ID label="ID">1503</METCONN_ID>
<METCONN_LIBELLE_METIER label="Nom du métier">giletier/ère</METCONN_LIBELLE_METIER>
<METCONN_SECTEUR_ACTIVITE label="Descripteur thesaurus Secteurs d'activité"/>
<METCONN_USER_MODIFICATION label="Utilisateur">edi</METCONN_USER_MODIFICATION>
<Thesaurus Level="1C1A" csRelFld="1503">
<CSTM_T Level="1C1A1"/>
</Thesaurus>
</record>
</METIER_CONNEXE>
</Métiers_associés>
<XML>
<XMLCONTENT>
<record Level="1D1" csKeyFld="16440" csRelFld="16440">
<CSLABELFLD label="">MET_NATURE_DESCRIPTIF</CSLABELFLD>
<XC_KEY label="XC_KEY">16440</XC_KEY>
<XC_TABLENAME label="Nom de la table à laquelle le fragment XML est rattaché">METIER</XC_TABLENAME>
<XC_RECKEY label="Identifiant unique de l'enregistrement concerné dans la table désigné par XC_TABLENAME">10396</XC_RECKEY>
<XC_TYPE label="Un texte permettant de différencier un fragment d'un autre pour un seul XC_RECKEY (ex.: Horaires, Ex">MET_NATURE_DESCRIPTIF</XC_TYPE>
<XC_XML label="Contenu XML résultant de la saisie. Il est extrait de XC_CONTENT après nettoyage des attributs inuti">
<MET_NATURE_DESCRIPTIF>
<inter>Des vêtements sur mesure</inter>
<p>Le tailleur-couturier réalise des vêtements sur mesure d'après les attentes d'un client. Il lui propose un modèle existant, en adapte un ou en crée un nouveau. Il le conseille sur la coupe du vêtement (droit, cintré, à pinces) en fonction de sa morphologie, et l'aide à choisir le tissu.</p>
<inter>Du patron aux finitions</inter>
<p>Après avoir pris les mensurations du client, le tailleur-couturier dessine un patron. Il réalise ensuite le vêtement dans sa totalité ou répartit les tâches entre plusieurs ouvriers. Il procède aux essayages et effectue des retouches, si nécessaire.</p>
<inter>Des spécialisations</inter>
<p>On distingue le tailleur, qui se consacre aux vêtements masculins, du couturier " flou ", spécialiste du vêtement féminin. Le tailleur peut être spécialisé dans l'une des étapes de la réalisation d'un costume. Il est ainsi appelé coupeur, s'il trace à la craie les contours du patron sur le tissu choisi, puis découpe les différents morceaux. Le saladeur prépare la " bûche ", c'est-à-dire les fournitures comme les sacs de poches ou les doublures. L'apiéceur assemble les morceaux et réalise les finitions. Quand il ne façonne que les pantalons de costume, le tailleur est appelé culottier. Le giletier façonne le gilet d'un complet, tandis que le boutonniériste se consacre aux boutonnières.</p>
</MET_NATURE_DESCRIPTIF>
</XC_XML>
</record>
<record Level="1D1" csKeyFld="16442" csRelFld="16442">
<CSLABELFLD label="">MET_ACCES_DESCRIPTIF</CSLABELFLD>
<XC_KEY label="XC_KEY">16442</XC_KEY>
<XC_TABLENAME label="Nom de la table à laquelle le fragment XML est rattaché">METIER</XC_TABLENAME>
<XC_RECKEY label="Identifiant unique de l'enregistrement concerné dans la table désigné par XC_TABLENAME">10396</XC_RECKEY>
<XC_TYPE label="Un texte permettant de différencier un fragment d'un autre pour un seul XC_RECKEY (ex.: Horaires, Ex">MET_ACCES_DESCRIPTIF</XC_TYPE>
<XC_XML label="Contenu XML résultant de la saisie. Il est extrait de XC_CONTENT après nettoyage des attributs inuti">
<MET_ACCES_DESCRIPTIF>
<p>Le métier de tailleur-couturier est accessible avec un CAP. Premier diplôme de la filière artisanale, il peut être complété, en cours d'emploi, par le BM (brevet de maîtrise) couturière ou tailleur ou par le BP (brevet professionnel) vêtement sur mesure, pour parfaire ses connaissances. Néanmoins, ce sont surtout l'expérience et la pratique qui permettent de maîtriser le geste. L'AFT (Association formation tailleur) délivre, par ailleurs, un titre de tailleur homme (2 ans de formation). Diverses formations (en 1 an) permettent de se spécialiser, par exemple en retouche, en stoppage, en broderie...</p>
<p>Le bac pro métiers de la mode-vêtements prépare davantage à un emploi de mécanicien modèle en atelier chargé de monter le vêtement, ou bien d'agent technique de bureau d'études/méthodes pour mettre au point le dossier de fabrication. Lui faisant suite, le BTS métiers de la mode option vêtement ouvre l'accès aux emplois de modéliste ou de technicien produit.</p>
<liste>
<tete>Après la 3<exp>e</exp>
</tete>
<itsimp>CAP métiers de la mode, option vêtement flou ou tailleur </itsimp>
</liste>
<liste>
<tete>Niveau bac</tete>
<itsimp>BM couturière ; tailleur, option dames ou messieurs</itsimp>
<itsimp>BP vêtement sur mesure, option A tailleur dame ; option B tailleur homme ; option C couture flou</itsimp>
<itsimp>Bac pro métiers de la mode-vêtements</itsimp>
</liste>
<liste>
<tete>Niveau bac + 2</tete>
<itsimp>BTS métiers de la mode, option vêtement</itsimp>
<itsimp>DMA costumier-réalisateur</itsimp>
</liste>
</MET_ACCES_DESCRIPTIF>
</XC_XML>
</record>
<record Level="1D1" csKeyFld="16439" csRelFld="16439">
<CSLABELFLD label="">MET_VIE_PRO_DESCRIPTIF</CSLABELFLD>
<XC_KEY label="XC_KEY">16439</XC_KEY>
<XC_TABLENAME label="Nom de la table à laquelle le fragment XML est rattaché">METIER</XC_TABLENAME>
<XC_RECKEY label="Identifiant unique de l'enregistrement concerné dans la table désigné par XC_TABLENAME">10396</XC_RECKEY>
<XC_TYPE label="Un texte permettant de différencier un fragment d'un autre pour un seul XC_RECKEY (ex.: Horaires, Ex">MET_VIE_PRO_DESCRIPTIF</XC_TYPE>
<XC_XML label="Contenu XML résultant de la saisie. Il est extrait de XC_CONTENT après nettoyage des attributs inuti">
<MET_VIE_PRO_DESCRIPTIF>
<inter>En petit nombre</inter>
<p>La France compte environ 6 000 artisans couturiers et seulement 150 ateliers de tailleurs, le sur-mesure ne représentant que 5 % du chiffre d'affaires de l'industrie française de l'habillement (source : Forthac, Fédération nationale des maîtres tailleurs, Unedic). Depuis quelques années, on assiste à un regain d'intérêt pour les vêtements sur mesure, mais les débouchés restent limités. Le tailleur-couturier peut s'installer à son compte après plusieurs années d'expérience et créer ses propres modèles.</p>
<inter>Du prêt-à-porter à la grande mesure</inter>
<p>Les entreprises artisanales peinent à résister à la concurrence industrielle, et les bénéfices restent faibles sur un produit fini. Cette concurrence est d'autant plus rude que les marques industrielles proposent désormais des services de demi-mesure, moins chers que la grande mesure (sur-mesure). Paradoxalement, l'apparition de la demi-mesure a amené de nouveaux clients aux tailleurs-couturiers : après avoir fait le choix de la demi-mesure, ces clients se tournent en effet souvent vers le sur-mesure.</p>
<inter>Se diversifier</inter>
<p>Pour résister à cette concurrence et augmenter ses revenus, le tailleur-couturier s'ouvre à la demi-mesure, voire au prêt-à-porter. Il peut aussi devenir tailleur-habilleur et vendre, dans sa boutique, des chemises, des cravates...</p>
<remun>
<inter>Salaire du débutant</inter>
<p>À partir du <sal>Smic</sal>.</p>
<postit>
<p>Source : Convention collective nationale des industries de l'habillement ; Convention collective nationale du commerce de détail de l'habillement et des articles textiles.</p>
</postit>
</remun>
</MET_VIE_PRO_DESCRIPTIF>
</XC_XML>
</record>
</XMLCONTENT>
</XML>
</metier>
