{
    "appelations": [
        {
            "libelle_court": "Cash manager",
            "priorisation": "1",
            "libelle": "Cash manager",
            "code_ogr": "11707"
        },
        {
            "libelle_court": "Charg\u00e9 / Charg\u00e9e de tr\u00e9sorerie et de financement",
            "priorisation": "1",
            "libelle": "Charg\u00e9 / Charg\u00e9e de tr\u00e9sorerie et de financement",
            "code_ogr": "11872"
        },
        {
            "libelle_court": "Consultant(e) financier(\u00e8re) sp\u00e9cialis\u00e9(e)",
            "priorisation": "1",
            "libelle": "Consultant financier sp\u00e9cialis\u00e9 / Consultante financi\u00e8re sp\u00e9cialis\u00e9e",
            "code_ogr": "13543"
        },
        {
            "libelle_court": "Credit controller",
            "priorisation": "1",
            "libelle": "Credit controller",
            "code_ogr": "13841"
        },
        {
            "libelle_court": "Credit manager",
            "priorisation": "1",
            "libelle": "Credit manager",
            "code_ogr": "13842"
        },
        {
            "libelle_court": "Directeur / Directrice de tr\u00e9sorerie",
            "priorisation": "1",
            "libelle": "Directeur / Directrice de tr\u00e9sorerie",
            "code_ogr": "14337"
        },
        {
            "libelle_court": "Expert financier / Experte financi\u00e8re",
            "priorisation": "1",
            "libelle": "Expert financier / Experte financi\u00e8re",
            "code_ogr": "14946"
        },
        {
            "libelle_court": "N\u00e9gociateur / N\u00e9gociatrice en devises",
            "priorisation": "1",
            "libelle": "N\u00e9gociateur / N\u00e9gociatrice en devises",
            "code_ogr": "16962"
        },
        {
            "libelle_court": "Responsable de la tr\u00e9sorerie",
            "priorisation": "1",
            "libelle": "Responsable de la tr\u00e9sorerie",
            "code_ogr": "18756"
        },
        {
            "libelle_court": "Responsable financement exportations",
            "priorisation": "1",
            "libelle": "Responsable financement exportations",
            "code_ogr": "19080"
        },
        {
            "libelle_court": "Responsable financement investissements",
            "priorisation": "1",
            "libelle": "Responsable financement investissements",
            "code_ogr": "19081"
        },
        {
            "libelle_court": "Responsable gestion tr\u00e9sorerie",
            "priorisation": "1",
            "libelle": "Responsable gestion tr\u00e9sorerie",
            "code_ogr": "19096"
        },
        {
            "libelle_court": "Responsable investissements",
            "priorisation": "1",
            "libelle": "Responsable investissements",
            "code_ogr": "19108"
        },
        {
            "libelle_court": "Responsable relations bancaires",
            "priorisation": "1",
            "libelle": "Responsable relations bancaires",
            "code_ogr": "19168"
        },
        {
            "libelle_court": "Tr\u00e9sorier / Tr\u00e9sori\u00e8re cr\u00e9dit manager",
            "priorisation": "1",
            "libelle": "Tr\u00e9sorier / Tr\u00e9sori\u00e8re cr\u00e9dit manager",
            "code_ogr": "20434"
        },
        {
            "libelle_court": "Tr\u00e9sorier / Tr\u00e9sori\u00e8re d'entreprise",
            "priorisation": "1",
            "libelle": "Tr\u00e9sorier / Tr\u00e9sori\u00e8re d'entreprise",
            "code_ogr": "20435"
        },
        {
            "libelle_court": "Tr\u00e9sorier / Tr\u00e9sori\u00e8re devises",
            "priorisation": "1",
            "libelle": "Tr\u00e9sorier / Tr\u00e9sori\u00e8re devises",
            "code_ogr": "20436"
        },
        {
            "libelle_court": "Tr\u00e9sorier / Tr\u00e9sori\u00e8re euros",
            "priorisation": "1",
            "libelle": "Tr\u00e9sorier / Tr\u00e9sori\u00e8re euros",
            "code_ogr": "20438"
        },
        {
            "libelle_court": "Tr\u00e9sorier / Tr\u00e9sori\u00e8re euros-devises",
            "priorisation": "1",
            "libelle": "Tr\u00e9sorier / Tr\u00e9sori\u00e8re euros-devises",
            "code_ogr": "20439"
        },
        {
            "libelle_court": "Tr\u00e9sorier / Tr\u00e9sori\u00e8re march\u00e9 mon\u00e9taire",
            "priorisation": "1",
            "libelle": "Tr\u00e9sorier / Tr\u00e9sori\u00e8re march\u00e9 mon\u00e9taire",
            "code_ogr": "20440"
        },
        {
            "libelle_court": "Tr\u00e9sorier adjoint / Tr\u00e9sori\u00e8re adjointe",
            "priorisation": "1",
            "libelle": "Tr\u00e9sorier adjoint / Tr\u00e9sori\u00e8re adjointe",
            "code_ogr": "20433"
        }
    ],
    "activites_de_base": [
        {
            "libelle": "Suivre les positions de tr\u00e9sorerie et en contr\u00f4ler la prise en compte comptable",
            "code_ogr": "3264",
            "code_type_activite": "2",
            "riasec_majeur": "C",
            "position_item": "1",
            "code_type_item_activite": "2",
            "priorisation": "1"
        },
        {
            "libelle": "Etablir la tr\u00e9sorerie pr\u00e9visionnelle dans le respect des ratios financiers d'endettement, de solvabilit\u00e9, de fond de roulement",
            "code_ogr": "1848",
            "code_type_activite": "2",
            "riasec_majeur": "C",
            "position_item": "2",
            "riasec_mineur": "i",
            "code_type_item_activite": "2",
            "priorisation": "1"
        },
        {
            "libelle": "Elaborer le budget de tr\u00e9sorerie selon les \u00e9l\u00e9ments comptables et financiers de l'entreprise et l'historique de son activit\u00e9",
            "code_ogr": "1726",
            "code_type_activite": "2",
            "riasec_majeur": "C",
            "position_item": "3",
            "riasec_mineur": "i",
            "code_type_item_activite": "2",
            "priorisation": "1"
        },
        {
            "libelle": "D\u00e9terminer les besoins en financement ou les disponibilit\u00e9s financi\u00e8res de la structure et mettre en place les actions adapt\u00e9es (ligne de cr\u00e9dit, investissement, ...)",
            "code_ogr": "1420",
            "code_type_activite": "2",
            "riasec_majeur": "E",
            "position_item": "4",
            "riasec_mineur": "c",
            "code_type_item_activite": "2",
            "priorisation": "1"
        },
        {
            "libelle": "Evaluer les flux financiers entrants ou sortants de la structure et en d\u00e9finir les proc\u00e9dures de traitement et de s\u00e9curisation",
            "code_ogr": "1956",
            "code_type_activite": "2",
            "riasec_majeur": "C",
            "position_item": "5",
            "code_type_item_activite": "2",
            "priorisation": "1"
        },
        {
            "libelle": "D\u00e9tecter les fragilit\u00e9s financi\u00e8res de la structure et \u00e9mettre des recommandations de gestion",
            "code_ogr": "1384",
            "code_type_activite": "2",
            "riasec_majeur": "C",
            "position_item": "6",
            "riasec_mineur": "i",
            "code_type_item_activite": "2",
            "priorisation": "1"
        }
    ],
    "mobilites_proches": [
        {
            "code_rome_cible": "M1201",
            "libelle_rome_cible": "Analyse et ing\u00e9nierie financi\u00e8re"
        }
    ],
    "acces_emploi_metier": "\nCet emploi/m\u00e9tier est accessible avec un Master (M1, Master professionnel, dipl\u00f4me d'\u00e9cole de commerce, ...) en \u00e9conomie, finance, commerce ou gestion compl\u00e9t\u00e9 par une exp\u00e9rience professionnelle dans le secteur.\nLa ma\u00eetrise d'une langue \u00e9trang\u00e8re, en particulier l'anglais, est requise.\n",
    "activite_specifique": [
        {
            "libelle": "D\u00e9finir et mettre en place une politique de cr\u00e9dit en direction des clients (contr\u00f4le de solvabilit\u00e9, garanties, encours, ...)",
            "code_ogr": "4513",
            "code_type_activite": "1",
            "riasec_majeur": "E",
            "position_item": "1",
            "riasec_mineur": "c",
            "code_type_item_activite": "2",
            "priorisation": "1"
        },
        {
            "libelle": "Apporter un appui technique en mati\u00e8re de litiges et de montages financiers pour une fusion, un rachat de filiale, ...",
            "code_ogr": "3811",
            "code_type_activite": "1",
            "riasec_majeur": "R",
            "position_item": "1",
            "riasec_mineur": "s",
            "code_type_item_activite": "2",
            "priorisation": "1"
        },
        {
            "libelle": "Rechercher des partenaires (banque, soci\u00e9t\u00e9 d'affacturage, ...) et des solutions de financement d'importation ou de recouvrement d'exportations",
            "code_ogr": "9446",
            "code_type_activite": "1",
            "riasec_majeur": "E",
            "position_item": "1",
            "riasec_mineur": "c",
            "code_type_item_activite": "2",
            "priorisation": "1"
        },
        {
            "libelle": "Suivre des relations bancaires (flux, ouverture de compte, ...) et participer aux n\u00e9gociations des co\u00fbts avec le directeur financier",
            "code_ogr": "9685",
            "code_type_activite": "1",
            "riasec_majeur": "E",
            "position_item": "1",
            "riasec_mineur": "c",
            "code_type_item_activite": "2",
            "priorisation": "1"
        },
        {
            "libelle": "R\u00e9aliser des virements de liquidit\u00e9s sur les comptes des filiales du groupe, r\u00e9gler des factures internes et transmettre \u00e0 la comptabilit\u00e9 pour consolidation",
            "code_ogr": "9138",
            "code_type_activite": "1",
            "riasec_majeur": "C",
            "position_item": "1",
            "code_type_item_activite": "2",
            "priorisation": "1"
        },
        {
            "libelle": "D\u00e9finir et mettre en oeuvre des proc\u00e9dures de gestion de la tr\u00e9sorerie et contr\u00f4ler des proc\u00e9dures comptables",
            "code_ogr": "4508",
            "code_type_activite": "1",
            "riasec_majeur": "C",
            "position_item": "1",
            "code_type_item_activite": "2",
            "priorisation": "1"
        },
        {
            "libelle": "Coordonner l'activit\u00e9 d'une \u00e9quipe",
            "code_ogr": "3517",
            "code_type_activite": "3",
            "riasec_majeur": "E",
            "position_item": "1",
            "code_type_item_activite": "2",
            "priorisation": "1"
        }
    ],
    "condition_exercice_activite": "\nL'activit\u00e9 de cet emploi/m\u00e9tier s'exerce au sein de banques, d'entreprises (entreprises moyennes, multinationales, ...), en relation avec diff\u00e9rents services et intervenants (comptabilit\u00e9, administration des ventes, directeur financier, contr\u00f4leur de gestion, ...).\nElle varie selon le secteur (banque, entreprise commerciale, ...) et la taille de la structure (entreprises moyennes, multinationale, ...).\n",
    "savoir_action": [
        {
            "priorisation": "1",
            "libelle": "Calcul de ratios financiers",
            "code_ogr": "20806",
            "position_item": "1",
            "code_type_competence": "2"
        },
        {
            "priorisation": "1",
            "libelle": "Utilisation de logiciels de gestion comptable",
            "code_ogr": "21252",
            "position_item": "2",
            "code_type_competence": "2"
        }
    ],
    "parse_appellation": 1,
    "environnement_travail": [
        {
            "priorisation": "1",
            "libelle": "Entreprise Moyenne",
            "code_ogr": "23911",
            "code_type_section_env": "1"
        },
        {
            "priorisation": "1",
            "libelle": "Etablissement bancaire et financier",
            "code_ogr": "23914",
            "code_type_section_env": "1"
        },
        {
            "priorisation": "1",
            "libelle": "Grande entreprise",
            "code_ogr": "23950",
            "code_type_section_env": "1"
        }
    ],
    "savoir_theorique_et_proceduraux": [
        {
            "priorisation": "1",
            "libelle": "Comptabilit\u00e9 g\u00e9n\u00e9rale",
            "code_ogr": "21738",
            "position_item": "1",
            "code_type_competence": "1"
        },
        {
            "priorisation": "1",
            "libelle": "Comptabilit\u00e9 analytique",
            "code_ogr": "21737",
            "position_item": "2",
            "code_type_competence": "1"
        },
        {
            "priorisation": "1",
            "libelle": "Comptabilit\u00e9 publique",
            "code_ogr": "21739",
            "position_item": "3",
            "code_type_competence": "1"
        },
        {
            "priorisation": "1",
            "libelle": "Droit cambiaire",
            "code_ogr": "21792",
            "position_item": "4",
            "code_type_competence": "1"
        },
        {
            "priorisation": "1",
            "libelle": "Fiscalit\u00e9",
            "code_ogr": "21947",
            "position_item": "5",
            "code_type_competence": "1"
        },
        {
            "priorisation": "1",
            "libelle": "M\u00e9thodes de gestion des risques",
            "code_ogr": "22133",
            "position_item": "6",
            "code_type_competence": "1"
        },
        {
            "priorisation": "1",
            "libelle": "Math\u00e9matiques financi\u00e8res",
            "code_ogr": "22097",
            "position_item": "7",
            "code_type_competence": "1"
        },
        {
            "priorisation": "1",
            "libelle": "Normes comptables International Financial Reports Standards -IFRS-",
            "code_ogr": "22217",
            "position_item": "8",
            "code_type_competence": "1"
        },
        {
            "priorisation": "1",
            "libelle": "Analyse financi\u00e8re",
            "code_ogr": "21503",
            "position_item": "9",
            "code_type_competence": "1"
        },
        {
            "priorisation": "1",
            "libelle": "Typologie des facteurs de risques financiers",
            "code_ogr": "23351",
            "position_item": "10",
            "code_type_competence": "1"
        },
        {
            "priorisation": "1",
            "libelle": "Caract\u00e9ristiques des actifs financiers",
            "code_ogr": "21553",
            "position_item": "11",
            "code_type_competence": "1"
        },
        {
            "priorisation": "1",
            "libelle": "Loi de s\u00e9curit\u00e9 financi\u00e8re",
            "code_ogr": "22089",
            "position_item": "12",
            "code_type_competence": "1"
        },
        {
            "priorisation": "1",
            "libelle": "Droit commercial",
            "code_ogr": "21794",
            "position_item": "13",
            "code_type_competence": "1"
        },
        {
            "priorisation": "1",
            "libelle": "Droit \u00e9conomique",
            "code_ogr": "21808",
            "position_item": "14",
            "code_type_competence": "1"
        },
        {
            "priorisation": "1",
            "libelle": "Gestion comptable et administrative",
            "code_ogr": "21995",
            "position_item": "15",
            "code_type_competence": "1"
        },
        {
            "priorisation": "1",
            "libelle": "Gestion budg\u00e9taire",
            "code_ogr": "21994",
            "position_item": "16",
            "code_type_competence": "1"
        },
        {
            "priorisation": "1",
            "libelle": "Affacturage",
            "code_ogr": "21497",
            "position_item": "1",
            "code_type_competence": "1"
        },
        {
            "priorisation": "1",
            "libelle": "Economie des march\u00e9s financiers",
            "code_ogr": "21823",
            "position_item": "2",
            "code_type_competence": "1"
        },
        {
            "priorisation": "1",
            "libelle": "Techniques commerciales",
            "code_ogr": "23012",
            "position_item": "1",
            "code_type_competence": "1"
        },
        {
            "priorisation": "1",
            "libelle": "Contr\u00f4le de gestion",
            "code_ogr": "21754",
            "position_item": "1",
            "code_type_competence": "1"
        }
    ],
    "definition": "\nOptimise et s\u00e9curise les flux financiers (de tr\u00e9sorerie, d'exportations, ...) de l'entreprise en fonction des orientations de la politique financi\u00e8re et des r\u00e9glementations (financi\u00e8res, comptables et commerciales).\nPeut effectuer la gestion de la politique de recouvrement. Peut rechercher des partenaires et des solutions de financement pour l'entreprise.\nPeut coordonner une \u00e9quipe.\n",
    "intitule": "Tr\u00e9sorerie et financement",
    "code_ogr": "464",
    "code_rome": "M1207",
    "mobilites_si_evolution": [
        {
            "code_rome_cible": "K2111",
            "libelle_rome_cible": "Formation professionnelle"
        },
        {
            "code_rome_cible": "M1204",
            "libelle_rome_cible": "Contr\u00f4le de gestion"
        },
        {
            "code_rome_cible": "M1205",
            "libelle_rome_cible": "Direction administrative et financi\u00e8re"
        }
    ]
}