{
    "appelations": [
        {
            "libelle_court": "Chef de carri\u00e8re",
            "priorisation": "1",
            "libelle": "Chef de carri\u00e8re",
            "code_ogr": "12079"
        },
        {
            "libelle_court": "Chef de chantier de forage",
            "priorisation": "1",
            "libelle": "Chef de chantier de forage",
            "code_ogr": "12092"
        },
        {
            "libelle_court": "Chef de chantier p\u00e9trole, gaz",
            "priorisation": "1",
            "libelle": "Chef de chantier p\u00e9trole, gaz",
            "code_ogr": "12098"
        },
        {
            "libelle_court": "Chef de gisement",
            "priorisation": "1",
            "libelle": "Chef de gisement",
            "code_ogr": "12153"
        },
        {
            "libelle_court": "Chef de mission prospection mini\u00e8re",
            "priorisation": "1",
            "libelle": "Chef de mission prospection mini\u00e8re",
            "code_ogr": "12194"
        },
        {
            "libelle_court": "Chef d'exploitation de carri\u00e8re",
            "priorisation": "1",
            "libelle": "Chef d'exploitation de carri\u00e8re",
            "code_ogr": "12512"
        },
        {
            "libelle_court": "Chef d'exploitation de gisement",
            "priorisation": "1",
            "libelle": "Chef d'exploitation de gisement",
            "code_ogr": "12514"
        },
        {
            "libelle_court": "Chef porion / porionne",
            "priorisation": "1",
            "libelle": "Chef porion / porionne",
            "code_ogr": "12598"
        },
        {
            "libelle_court": "Ing\u00e9nieur(e) de compl\u00e9tion en exploitation des gisements",
            "priorisation": "1",
            "libelle": "Ing\u00e9nieur / Ing\u00e9nieure de compl\u00e9tion en exploitation des gisements",
            "code_ogr": "15629"
        },
        {
            "libelle_court": "Ing\u00e9nieur / Ing\u00e9nieure de forage",
            "priorisation": "1",
            "libelle": "Ing\u00e9nieur / Ing\u00e9nieure de forage",
            "code_ogr": "15639"
        },
        {
            "libelle_court": "Ing\u00e9nieur / Ing\u00e9nieure de gisement",
            "priorisation": "1",
            "libelle": "Ing\u00e9nieur / Ing\u00e9nieure de gisement",
            "code_ogr": "15642"
        },
        {
            "libelle_court": "Ing\u00e9nieur / Ing\u00e9nieure de production p\u00e9troli\u00e8re",
            "priorisation": "1",
            "libelle": "Ing\u00e9nieur / Ing\u00e9nieure de production p\u00e9troli\u00e8re",
            "code_ogr": "15661"
        },
        {
            "libelle_court": "Ing\u00e9nieur(e) de s\u00e9curit\u00e9 en exploitation de gisements",
            "priorisation": "1",
            "libelle": "Ing\u00e9nieur / Ing\u00e9nieure de s\u00e9curit\u00e9 en exploitation de gisements",
            "code_ogr": "15672"
        },
        {
            "libelle_court": "Ing\u00e9nieur / Ing\u00e9nieure de sonde",
            "priorisation": "1",
            "libelle": "Ing\u00e9nieur / Ing\u00e9nieure de sonde",
            "code_ogr": "15673"
        },
        {
            "libelle_court": "Ing\u00e9nieur / Ing\u00e9nieure d'exploitation de gisements",
            "priorisation": "1",
            "libelle": "Ing\u00e9nieur / Ing\u00e9nieure d'exploitation de gisements",
            "code_ogr": "15716"
        },
        {
            "libelle_court": "Ing\u00e9nieur / Ing\u00e9nieure d'installations mini\u00e8res",
            "priorisation": "1",
            "libelle": "Ing\u00e9nieur / Ing\u00e9nieure d'installations mini\u00e8res",
            "code_ogr": "15720"
        },
        {
            "libelle_court": "Porion / Porionne",
            "priorisation": "1",
            "libelle": "Porion / Porionne",
            "code_ogr": "17891"
        },
        {
            "libelle_court": "Responsable d'exploitation de gisements et de carri\u00e8res",
            "priorisation": "1",
            "libelle": "Responsable d'exploitation de gisements et de carri\u00e8res",
            "code_ogr": "18977"
        },
        {
            "libelle_court": "Statigraphe",
            "priorisation": "1",
            "libelle": "Statigraphe",
            "code_ogr": "19520"
        },
        {
            "libelle_court": "Stratigraphe",
            "priorisation": "1",
            "libelle": "Stratigraphe",
            "code_ogr": "19538"
        },
        {
            "libelle_court": "Technicien / Technicienne d'exploitation de gisement",
            "priorisation": "1",
            "libelle": "Technicien / Technicienne d'exploitation de gisement",
            "code_ogr": "19971"
        }
    ],
    "activites_de_base": [
        {
            "libelle": "D\u00e9terminer les zones d'exploitation ou d'extraction et planifier les interventions selon des donn\u00e9es techniques, r\u00e9glementaires et \u00e9conomiques",
            "code_ogr": "1450",
            "code_type_activite": "2",
            "riasec_majeur": "C",
            "position_item": "1",
            "riasec_mineur": "r",
            "code_type_item_activite": "2",
            "priorisation": "1"
        },
        {
            "libelle": "Organiser l'approvisionnement et le stockage du mat\u00e9riel, des engins et s\u00e9curiser le chantier",
            "code_ogr": "2464",
            "code_type_activite": "2",
            "riasec_majeur": "R",
            "position_item": "2",
            "riasec_mineur": "c",
            "code_type_item_activite": "2",
            "priorisation": "1"
        },
        {
            "libelle": "Concevoir les voies et infrastructures de circulation du site d'exploitation et de ses abords",
            "code_ogr": "910",
            "code_type_activite": "2",
            "riasec_majeur": "R",
            "position_item": "3",
            "riasec_mineur": "a",
            "code_type_item_activite": "2",
            "priorisation": "1"
        },
        {
            "libelle": "Concevoir et \u00e9tablir le plan de tir de mines selon les analyses g\u00e9ologiques, le volume \u00e0 extraire, ...",
            "code_ogr": "876",
            "code_type_activite": "2",
            "riasec_majeur": "I",
            "position_item": "4",
            "riasec_mineur": "c",
            "code_type_item_activite": "2",
            "priorisation": "1"
        },
        {
            "libelle": "Diriger des op\u00e9rations de forage (foration, tubage, cimentation, ...)",
            "code_ogr": "1472",
            "code_type_activite": "2",
            "riasec_majeur": "R",
            "position_item": "5",
            "riasec_mineur": "e",
            "code_type_item_activite": "2",
            "priorisation": "1"
        },
        {
            "libelle": "Suivre l'\u00e9volution du gisement et ajuster les param\u00e8tres d'exploitation selon la nature des roches et l'impact environnemental",
            "code_ogr": "3273",
            "code_type_activite": "2",
            "riasec_majeur": "C",
            "position_item": "6",
            "code_type_item_activite": "2",
            "priorisation": "1"
        },
        {
            "libelle": "Suivre et contr\u00f4ler le budget, les param\u00e8tres de production, de transformation et de stockage de produits",
            "code_ogr": "3225",
            "code_type_activite": "2",
            "riasec_majeur": "C",
            "position_item": "7",
            "code_type_item_activite": "2",
            "priorisation": "1"
        },
        {
            "libelle": "Coordonner les op\u00e9rations de r\u00e9am\u00e9nagement et de r\u00e9habilitation du site en fin d'exploitation",
            "code_ogr": "1200",
            "code_type_activite": "2",
            "riasec_majeur": "E",
            "position_item": "8",
            "riasec_mineur": "r",
            "code_type_item_activite": "2",
            "priorisation": "1"
        }
    ],
    "mobilites_proches": [
        {
            "code_rome_cible": "F1105",
            "libelle_rome_cible": "\u00c9tudes g\u00e9ologiques"
        },
        {
            "code_rome_cible": "F1201",
            "libelle_rome_cible": "Conduite de travaux du BTP"
        },
        {
            "code_rome_cible": "F1202",
            "libelle_rome_cible": "Direction de chantier du BTP"
        }
    ],
    "acces_emploi_metier": "\nCet emploi/m\u00e9tier est accessible avec un dipl\u00f4me de niveau Bac+2 (BTS, ...) \u00e0 Bac+5 (Master, Dipl\u00f4me d'ing\u00e9nieur, ...) dans les secteurs de l'extraction, travaux publics.\nDes formations compl\u00e9mentaires sur la pr\u00e9vention et les risques inh\u00e9rents aux \u00e9ruptions peuvent \u00eatre requises.\nLe Certificat de Pr\u00e9pos\u00e9 au Tir -CPT- est exig\u00e9 pour les op\u00e9rations de mise en oeuvre de produits explosifs.\n",
    "activite_specifique": [
        {
            "libelle": "Superviser des forages d'extraction :",
            "code_ogr": "0",
            "code_type_activite": "0",
            "position_item": "0",
            "code_type_item_activite": "0",
            "priorisation": "1"
        },
        {
            "libelle": "Maritime (off-shore)",
            "code_ogr": "9746",
            "code_type_activite": "1",
            "riasec_majeur": "E",
            "position_item": "1",
            "riasec_mineur": "i",
            "code_type_item_activite": "1",
            "priorisation": "1"
        },
        {
            "libelle": "Terrestre (on-shore)",
            "code_ogr": "9747",
            "code_type_activite": "1",
            "riasec_majeur": "E",
            "position_item": "2",
            "riasec_mineur": "i",
            "code_type_item_activite": "1",
            "priorisation": "1"
        },
        {
            "libelle": "Extraire des roches n\u00e9cessitant le Certificat de Pr\u00e9pos\u00e9 au Tir -CPT-",
            "code_ogr": "5897",
            "code_type_activite": "1",
            "riasec_majeur": "R",
            "position_item": "1",
            "code_type_item_activite": "2",
            "priorisation": "1"
        },
        {
            "libelle": "Etablir des documents administratifs li\u00e9s \u00e0 l'exploitation d'un site (contrats de travail, Plan d'Assurance Qualit\u00e9, plan de contr\u00f4le des polluants, ...)",
            "code_ogr": "5802",
            "code_type_activite": "1",
            "riasec_majeur": "C",
            "position_item": "1",
            "code_type_item_activite": "2",
            "priorisation": "1"
        },
        {
            "libelle": "Superviser le fonctionnement des installations de traitement et de transformation des mat\u00e9riaux (pilotage, r\u00e9glage, ...)",
            "code_ogr": "9778",
            "code_type_activite": "1",
            "riasec_majeur": "C",
            "position_item": "1",
            "code_type_item_activite": "2",
            "priorisation": "1"
        },
        {
            "libelle": "Actualiser les plans g\u00e9ologiques d'une exploitation",
            "code_ogr": "3667",
            "code_type_activite": "1",
            "riasec_majeur": "R",
            "position_item": "1",
            "code_type_item_activite": "2",
            "priorisation": "1"
        },
        {
            "libelle": "Contr\u00f4ler la conformit\u00e9 de r\u00e9alisations de fournisseurs, sous-traitants, prestataires",
            "code_ogr": "3513",
            "code_type_activite": "3",
            "riasec_majeur": "C",
            "position_item": "1",
            "code_type_item_activite": "2",
            "priorisation": "1"
        },
        {
            "libelle": "Analyser des forations et le r\u00e9sultat de tirs de mines",
            "code_ogr": "3710",
            "code_type_activite": "1",
            "riasec_majeur": "R",
            "position_item": "1",
            "riasec_mineur": "c",
            "code_type_item_activite": "2",
            "priorisation": "1"
        },
        {
            "libelle": "Analyser des \u00e9chantillons de front de taille sous-terrain",
            "code_ogr": "3707",
            "code_type_activite": "1",
            "riasec_majeur": "C",
            "position_item": "1",
            "riasec_mineur": "r",
            "code_type_item_activite": "2",
            "priorisation": "1"
        },
        {
            "libelle": "Commercialiser des produits d'extraction du site",
            "code_ogr": "3916",
            "code_type_activite": "1",
            "riasec_majeur": "E",
            "position_item": "1",
            "riasec_mineur": "r",
            "code_type_item_activite": "2",
            "priorisation": "1"
        },
        {
            "libelle": "Informer et renseigner les autorit\u00e9s locales, les usagers, les riverains, les associations sur l'exploitation (impact, circulation, ...)",
            "code_ogr": "6160",
            "code_type_activite": "1",
            "riasec_majeur": "S",
            "position_item": "1",
            "code_type_item_activite": "2",
            "priorisation": "1"
        },
        {
            "libelle": "Coordonner l'activit\u00e9 d'une \u00e9quipe",
            "code_ogr": "3517",
            "code_type_activite": "3",
            "riasec_majeur": "E",
            "position_item": "1",
            "code_type_item_activite": "2",
            "priorisation": "1"
        }
    ],
    "condition_exercice_activite": "\nL'activit\u00e9 de cet emploi/m\u00e9tier s'exerce sur des chantiers, des carri\u00e8res, des mines \u00e0 ciel ouvert au sein d'entreprises d'extraction de produits solides, liquides ou gazeux, en relation avec diff\u00e9rents intervenants (g\u00e9ologues, g\u00e9otechniciens, fournisseurs, acheteurs, collectivit\u00e9s locales, institutionnels.\nElle peut impliquer des d\u00e9placements et un \u00e9loignement du domicile de plusieurs jours ou mois.\nElle peut s'exercer les fins de semaine, jours f\u00e9ri\u00e9s, de nuit et \u00eatre soumise \u00e0 des astreintes.\nLe port d'\u00e9quipements de protection (casque de chantier, gants, ...) est requis.\n",
    "savoir_action": [
        {
            "priorisation": "1",
            "libelle": "Utilisation de logiciel de cartographie",
            "code_ogr": "21225",
            "position_item": "1",
            "code_type_competence": "2"
        },
        {
            "priorisation": "1",
            "libelle": "Utilisation de logiciels de gestion de stocks",
            "code_ogr": "21259",
            "position_item": "2",
            "code_type_competence": "2"
        },
        {
            "priorisation": "1",
            "libelle": "Utilisation d'outils bureautiques (traitement de texte, tableur,...)",
            "code_ogr": "21467",
            "position_item": "1",
            "code_type_competence": "2"
        }
    ],
    "parse_appellation": 1,
    "environnement_travail": [
        {
            "priorisation": "1",
            "libelle": "Entreprise de forage/extraction",
            "code_ogr": "23877",
            "code_type_section_env": "1"
        },
        {
            "priorisation": "1",
            "libelle": "Eau",
            "code_ogr": "23467",
            "code_type_section_env": "2"
        },
        {
            "priorisation": "1",
            "libelle": "Gaz",
            "code_ogr": "23508",
            "code_type_section_env": "2"
        },
        {
            "priorisation": "1",
            "libelle": "P\u00e9trole",
            "code_ogr": "23583",
            "code_type_section_env": "2"
        }
    ],
    "savoir_theorique_et_proceduraux": [
        {
            "priorisation": "1",
            "libelle": "R\u00e8gles et consignes de s\u00e9curit\u00e9",
            "code_ogr": "22656",
            "position_item": "1",
            "code_type_competence": "1"
        },
        {
            "priorisation": "1",
            "libelle": "R\u00e9glementation G\u00e9n\u00e9rale des Industries Extractives -RGIE-",
            "code_ogr": "22570",
            "position_item": "2",
            "code_type_competence": "1"
        },
        {
            "priorisation": "1",
            "libelle": "Caract\u00e9ristiques des engins de chantier",
            "code_ogr": "21575",
            "position_item": "3",
            "code_type_competence": "1"
        },
        {
            "priorisation": "1",
            "libelle": "G\u00e9ologie",
            "code_ogr": "21984",
            "position_item": "4",
            "code_type_competence": "1"
        },
        {
            "priorisation": "1",
            "libelle": "G\u00e9otechnique",
            "code_ogr": "21988",
            "position_item": "5",
            "code_type_competence": "1"
        },
        {
            "priorisation": "1",
            "libelle": "G\u00e9othermie",
            "code_ogr": "21989",
            "position_item": "6",
            "code_type_competence": "1"
        },
        {
            "priorisation": "1",
            "libelle": "Cartographie",
            "code_ogr": "21695",
            "position_item": "7",
            "code_type_competence": "1"
        },
        {
            "priorisation": "1",
            "libelle": "Normes environnementales",
            "code_ogr": "22230",
            "position_item": "8",
            "code_type_competence": "1"
        },
        {
            "priorisation": "1",
            "libelle": "Topographie",
            "code_ogr": "23284",
            "position_item": "9",
            "code_type_competence": "1"
        }
    ],
    "definition": "\nCoordonne l'ensemble des op\u00e9rations d'extraction, de transport sur site, de traitement et d'exp\u00e9dition des mat\u00e9riaux solides, liquides ou gazeux issus de leur milieu naturel selon les normes de s\u00e9curit\u00e9.\n",
    "intitule": "Direction et ing\u00e9nierie d'exploitation de gisements et de carri\u00e8res",
    "code_ogr": "152",
    "code_rome": "F1203",
    "mobilites_si_evolution": [
        {
            "code_rome_cible": "F1204",
            "libelle_rome_cible": "S\u00e9curit\u00e9 et protection sant\u00e9 du BTP"
        },
        {
            "code_rome_cible": "H1302",
            "libelle_rome_cible": "Management et ing\u00e9nierie Hygi\u00e8ne S\u00e9curit\u00e9 Environnement -HSE- industriels"
        },
        {
            "code_rome_cible": "K2306",
            "libelle_rome_cible": "Supervision d'exploitation \u00e9co-industrielle"
        }
    ]
}