{
    "appelations": [
        {
            "libelle_court": "Agent / Agente technique de fabrication d'imprimerie",
            "priorisation": "1",
            "libelle": "Agent / Agente technique de fabrication d'imprimerie",
            "code_ogr": "10771"
        },
        {
            "libelle_court": "Agent/Agente technique de fabrication en industrie graphique",
            "priorisation": "1",
            "libelle": "Agent / Agente technique de fabrication en industrie graphique",
            "code_ogr": "10772"
        },
        {
            "libelle_court": "Agent(e) de fabrication-deviseur(se) en industrie graphique",
            "priorisation": "1",
            "libelle": "Agent de fabrication-deviseur / Agente de fabrication-deviseuse en industrie graphique",
            "code_ogr": "10454"
        },
        {
            "libelle_court": "Contr\u00f4leur / Contr\u00f4leuse qualit\u00e9 en industrie graphique",
            "priorisation": "1",
            "libelle": "Contr\u00f4leur / Contr\u00f4leuse qualit\u00e9 en industrie graphique",
            "code_ogr": "13649"
        },
        {
            "libelle_court": "Deviseur / Deviseuse en industrie graphique",
            "priorisation": "1",
            "libelle": "Deviseur / Deviseuse en industrie graphique",
            "code_ogr": "14159"
        },
        {
            "libelle_court": "Fabricant / Fabricante en industrie graphique",
            "priorisation": "1",
            "libelle": "Fabricant / Fabricante en industrie graphique",
            "code_ogr": "15027"
        },
        {
            "libelle_court": "Responsable de fabrication en industrie graphique",
            "priorisation": "1",
            "libelle": "Responsable de fabrication en industrie graphique",
            "code_ogr": "18710"
        },
        {
            "libelle_court": "Responsable de planning en industrie graphique",
            "priorisation": "1",
            "libelle": "Responsable de planning en industrie graphique",
            "code_ogr": "18805"
        },
        {
            "libelle_court": "Simulateur / Simulatrice d'impression en industrie graphique",
            "priorisation": "1",
            "libelle": "Simulateur / Simulatrice d'impression en industrie graphique",
            "code_ogr": "19434"
        },
        {
            "libelle_court": "Support produit en industrie graphique",
            "priorisation": "1",
            "libelle": "Support produit en industrie graphique",
            "code_ogr": "19576"
        },
        {
            "libelle_court": "Technicien / Technicienne de fabrication d'\u00e9dition",
            "priorisation": "1",
            "libelle": "Technicien / Technicienne de fabrication d'\u00e9dition",
            "code_ogr": "19758"
        },
        {
            "libelle_court": "Technicien(ne) de fabrication en industrie graphique",
            "priorisation": "1",
            "libelle": "Technicien / Technicienne de fabrication en industrie graphique",
            "code_ogr": "19762"
        },
        {
            "libelle_court": "Technicien(ne) de fabrication-deviseur en ind graphique",
            "priorisation": "1",
            "libelle": "Technicien / Technicienne de fabrication-deviseur en industrie graphique",
            "code_ogr": "19770"
        },
        {
            "libelle_court": "Technicien(ne) de laboratoire en industrie graphique",
            "priorisation": "1",
            "libelle": "Technicien / Technicienne de laboratoire en industrie graphique",
            "code_ogr": "19805"
        },
        {
            "libelle_court": "Technicien/Technicienne de pr\u00e9paration contr\u00f4le composition",
            "priorisation": "1",
            "libelle": "Technicien / Technicienne de pr\u00e9paration contr\u00f4le composition",
            "code_ogr": "19896"
        },
        {
            "libelle_court": "Technicien(ne) de pr\u00e9paration contr\u00f4le impression-finition",
            "priorisation": "1",
            "libelle": "Technicien / Technicienne de pr\u00e9paration contr\u00f4le impression-finition",
            "code_ogr": "19897"
        },
        {
            "libelle_court": "Technicien/Technicienne de pr\u00e9paration contr\u00f4le photogravure",
            "priorisation": "1",
            "libelle": "Technicien / Technicienne de pr\u00e9paration contr\u00f4le photogravure",
            "code_ogr": "19898"
        },
        {
            "libelle_court": "Technicien / Technicienne des industries graphiques",
            "priorisation": "1",
            "libelle": "Technicien / Technicienne des industries graphiques",
            "code_ogr": "19948"
        },
        {
            "libelle_court": "Technicien(ne) essai-contr\u00f4le qualit\u00e9 en ind graphique",
            "priorisation": "1",
            "libelle": "Technicien / Technicienne essai-contr\u00f4le qualit\u00e9 en industrie graphique",
            "code_ogr": "20136"
        },
        {
            "libelle_court": "Technicien(ne) \u00e9tudes-recherche-d\u00e9veloppement ind graphique",
            "priorisation": "1",
            "libelle": "Technicien / Technicienne \u00e9tudes-recherche-d\u00e9veloppement en industrie graphique",
            "code_ogr": "20139"
        },
        {
            "libelle_court": "Technicien(ne) sup\u00e9rieur(e) en industrie graphique",
            "priorisation": "1",
            "libelle": "Technicien sup\u00e9rieur / Technicienne sup\u00e9rieure en industrie graphique",
            "code_ogr": "20270"
        }
    ],
    "activites_de_base": [
        {
            "libelle": "Pr\u00e9senter au client les am\u00e9liorations envisageables (grammage papier, mise en page, ...) apr\u00e8s avoir v\u00e9rifi\u00e9 la faisabilit\u00e9 de la commande",
            "code_ogr": "3422",
            "code_type_activite": "2",
            "riasec_majeur": "C",
            "position_item": "1",
            "riasec_mineur": "e",
            "code_type_item_activite": "2",
            "priorisation": "1"
        },
        {
            "libelle": "Analyser et d\u00e9finir les proc\u00e9d\u00e9s, les moyens de production et de contr\u00f4le, les modes op\u00e9ratoires",
            "code_ogr": "632",
            "code_type_activite": "2",
            "riasec_majeur": "I",
            "position_item": "2",
            "code_type_item_activite": "2",
            "priorisation": "1"
        },
        {
            "libelle": "Elaborer le dossier de production (imp\u00e9ratifs techniques, types de supports, encres, finitions, quantit\u00e9s, ...) et r\u00e9diger les ordres de fabrication",
            "code_ogr": "1729",
            "code_type_activite": "2",
            "riasec_majeur": "C",
            "position_item": "3",
            "riasec_mineur": "r",
            "code_type_item_activite": "2",
            "priorisation": "1"
        },
        {
            "libelle": "Elaborer et faire \u00e9voluer les proc\u00e9dures (gammes, fiches de fabrication, r\u00e9f\u00e9rentiels qualit\u00e9, ...) et contr\u00f4ler la conformit\u00e9 de leur application",
            "code_ogr": "1706",
            "code_type_activite": "2",
            "riasec_majeur": "I",
            "position_item": "4",
            "riasec_mineur": "r",
            "code_type_item_activite": "2",
            "priorisation": "1"
        },
        {
            "libelle": "Chiffrer les co\u00fbts et temps de fabrication et \u00e9tablir les standards de prix et les devis",
            "code_ogr": "818",
            "code_type_activite": "2",
            "riasec_majeur": "C",
            "position_item": "5",
            "code_type_item_activite": "2",
            "priorisation": "1"
        },
        {
            "libelle": "Etablir les plannings de production et les programmes fabrication",
            "code_ogr": "1885",
            "code_type_activite": "2",
            "riasec_majeur": "C",
            "position_item": "6",
            "riasec_mineur": "r",
            "code_type_item_activite": "2",
            "priorisation": "1"
        },
        {
            "libelle": "Rep\u00e9rer les besoins en sous-traitance, s\u00e9lectionner les intervenants et effectuer le suivi des actions",
            "code_ogr": "3604",
            "code_type_activite": "3",
            "riasec_majeur": "E",
            "position_item": "7",
            "code_type_item_activite": "2",
            "priorisation": "1"
        },
        {
            "libelle": "Contr\u00f4ler la conformit\u00e9 de l'\u00e9preuve par rapport \u00e0 la commande et \u00e9tablir le Bon A Tirer",
            "code_ogr": "3512",
            "code_type_activite": "3",
            "riasec_majeur": "C",
            "position_item": "8",
            "code_type_item_activite": "2",
            "priorisation": "1"
        }
    ],
    "mobilites_proches": [
        {
            "code_rome_cible": "E1303",
            "libelle_rome_cible": "Encadrement des industries graphiques"
        }
    ],
    "acces_emploi_metier": "\nCet emploi/m\u00e9tier est accessible avec un dipl\u00f4me de niveau Bac+2 (BTS, DUT, ...) en communication et industries graphiques.\nIl est \u00e9galement accessible avec un dipl\u00f4me de niveau CAP/BEP \u00e0 Bac (professionnel, ...) en production graphique, production imprim\u00e9e compl\u00e9t\u00e9 par une exp\u00e9rience professionnelle dans le m\u00eame secteur.\nUne Licence professionnelle en industries graphiques peut \u00eatre demand\u00e9e.\nLa pratique d'une langue \u00e9trang\u00e8re peut \u00eatre exig\u00e9e.\nLa ma\u00eetrise de l'outil informatique (logiciels de bureautique, gestion de production, Publication Assist\u00e9e par Ordinateur -PAO-, ...) est requise.\n",
    "activite_specifique": [
        {
            "libelle": "Pr\u00e9parer des documents pour un type d'impression ou de marquage :",
            "code_ogr": "0",
            "code_type_activite": "0",
            "position_item": "0",
            "code_type_item_activite": "0",
            "priorisation": "1"
        },
        {
            "libelle": "Flexographie",
            "code_ogr": "7923",
            "code_type_activite": "1",
            "riasec_majeur": "R",
            "position_item": "1",
            "code_type_item_activite": "1",
            "priorisation": "1"
        },
        {
            "libelle": "Gravure laser",
            "code_ogr": "38758",
            "code_type_activite": "1",
            "riasec_majeur": "R",
            "position_item": "2",
            "riasec_mineur": "a",
            "code_type_item_activite": "1",
            "priorisation": "1"
        },
        {
            "libelle": "Gravure m\u00e9canique",
            "code_ogr": "38759",
            "code_type_activite": "1",
            "riasec_majeur": "R",
            "position_item": "3",
            "riasec_mineur": "a",
            "code_type_item_activite": "1",
            "priorisation": "1"
        },
        {
            "libelle": "H\u00e9liogravure",
            "code_ogr": "7924",
            "code_type_activite": "1",
            "riasec_majeur": "R",
            "position_item": "4",
            "code_type_item_activite": "1",
            "priorisation": "1"
        },
        {
            "libelle": "Lithographie",
            "code_ogr": "7925",
            "code_type_activite": "1",
            "riasec_majeur": "R",
            "position_item": "5",
            "code_type_item_activite": "1",
            "priorisation": "1"
        },
        {
            "libelle": "Num\u00e9rique",
            "code_ogr": "7926",
            "code_type_activite": "1",
            "riasec_majeur": "R",
            "position_item": "6",
            "code_type_item_activite": "1",
            "priorisation": "1"
        },
        {
            "libelle": "Offset",
            "code_ogr": "7927",
            "code_type_activite": "1",
            "riasec_majeur": "R",
            "position_item": "7",
            "code_type_item_activite": "1",
            "priorisation": "1"
        },
        {
            "libelle": "S\u00e9rigraphie",
            "code_ogr": "7928",
            "code_type_activite": "1",
            "riasec_majeur": "R",
            "position_item": "8",
            "code_type_item_activite": "1",
            "priorisation": "1"
        },
        {
            "libelle": "Taille douce",
            "code_ogr": "7929",
            "code_type_activite": "1",
            "riasec_majeur": "R",
            "position_item": "9",
            "code_type_item_activite": "1",
            "priorisation": "1"
        },
        {
            "libelle": "Tampographie",
            "code_ogr": "7930",
            "code_type_activite": "1",
            "riasec_majeur": "R",
            "position_item": "10",
            "code_type_item_activite": "1",
            "priorisation": "1"
        },
        {
            "libelle": "Typogravure",
            "code_ogr": "7931",
            "code_type_activite": "1",
            "riasec_majeur": "R",
            "position_item": "11",
            "code_type_item_activite": "1",
            "priorisation": "1"
        },
        {
            "libelle": "Concevoir des supports de communication (graphiques, multim\u00e9dias, papier, ...)",
            "code_ogr": "3989",
            "code_type_activite": "1",
            "riasec_majeur": "A",
            "position_item": "1",
            "code_type_item_activite": "2",
            "priorisation": "1"
        },
        {
            "libelle": "Elaborer des supports de suivi de fabrication de produits graphiques (tableau de bord, d\u00e9finition d'indicateurs, ...)",
            "code_ogr": "5596",
            "code_type_activite": "1",
            "riasec_majeur": "C",
            "position_item": "1",
            "code_type_item_activite": "2",
            "priorisation": "1"
        },
        {
            "libelle": "V\u00e9rifier des donn\u00e9es et des \u00e9tapes de production en industrie graphique (quantit\u00e9s, types de production, dysfonctionnements, d\u00e9lais, ...)",
            "code_ogr": "10161",
            "code_type_activite": "1",
            "riasec_majeur": "C",
            "position_item": "1",
            "code_type_item_activite": "2",
            "priorisation": "1"
        },
        {
            "libelle": "Elaborer des solutions techniques et organisationnelles d'am\u00e9lioration de production",
            "code_ogr": "5595",
            "code_type_activite": "1",
            "riasec_majeur": "R",
            "position_item": "1",
            "riasec_mineur": "e",
            "code_type_item_activite": "2",
            "priorisation": "1"
        },
        {
            "libelle": "Elaborer et faire \u00e9voluer des proc\u00e9dures de maintenance de machines et d'\u00e9quipements en industrie graphique (machines d'impression, de fa\u00e7onnage, ...)",
            "code_ogr": "5608",
            "code_type_activite": "1",
            "riasec_majeur": "I",
            "position_item": "1",
            "riasec_mineur": "r",
            "code_type_item_activite": "2",
            "priorisation": "1"
        },
        {
            "libelle": "Suivre l'\u00e9tat des stocks de produits, identifier les besoins en approvisionnement et transmettre la commande \u00e0 l'interlocuteur concern\u00e9",
            "code_ogr": "3616",
            "code_type_activite": "3",
            "riasec_majeur": "C",
            "position_item": "1",
            "code_type_item_activite": "2",
            "priorisation": "1"
        },
        {
            "libelle": "Planifier l'activit\u00e9 des personnels et les affecter sur les postes",
            "code_ogr": "3575",
            "code_type_activite": "3",
            "riasec_majeur": "E",
            "position_item": "1",
            "riasec_mineur": "r",
            "code_type_item_activite": "2",
            "priorisation": "1"
        },
        {
            "libelle": "Suivre et v\u00e9rifier les \u00e9l\u00e9ments d'activit\u00e9 et de gestion administrative du personnel",
            "code_ogr": "3613",
            "code_type_activite": "3",
            "riasec_majeur": "C",
            "position_item": "1",
            "code_type_item_activite": "2",
            "priorisation": "1"
        }
    ],
    "condition_exercice_activite": "\nL'activit\u00e9 de cet emploi/m\u00e9tier s'exerce au sein d'entreprises d'impression/fa\u00e7onnage (imprimerie de labeur, d'\u00e9dition, de presse, ...) ou d'imprimeries int\u00e9gr\u00e9es aux entreprises, en relation avec diff\u00e9rents services (pr\u00e9presse, fa\u00e7onnage, impression, achats, qualit\u00e9, ...).\nElle varie selon le secteur (imprimerie de labeur, de presse, ...), la taille de l'entreprise, la technique d'impression (s\u00e9rigraphie, flexographie, ...), le degr\u00e9 d'automatisation du site.\nElle peut s'exercer les fins de semaine, jours f\u00e9ri\u00e9s.\n",
    "savoir_action": [
        {
            "priorisation": "1",
            "libelle": "Utilisation d'outils bureautiques (traitement de texte, tableur,...)",
            "code_ogr": "21467",
            "position_item": "1",
            "code_type_competence": "2"
        },
        {
            "priorisation": "1",
            "libelle": "Chiffrage/calcul de co\u00fbt",
            "code_ogr": "20813",
            "position_item": "2",
            "code_type_competence": "2"
        },
        {
            "priorisation": "1",
            "libelle": "Elaboration de devis",
            "code_ogr": "20868",
            "position_item": "3",
            "code_type_competence": "2"
        },
        {
            "priorisation": "1",
            "libelle": "Utilisation de logiciels de Publication Assist\u00e9e par Ordinateur -PAO-",
            "code_ogr": "21264",
            "position_item": "4",
            "code_type_competence": "2"
        },
        {
            "priorisation": "1",
            "libelle": "Utilisation de logiciels de Gestion de Production Assist\u00e9e Par Ordinateur -GPAO-",
            "code_ogr": "21258",
            "position_item": "5",
            "code_type_competence": "2"
        },
        {
            "priorisation": "1",
            "libelle": "Utilisation de logiciels de gestion de planning",
            "code_ogr": "21257",
            "position_item": "6",
            "code_type_competence": "2"
        },
        {
            "priorisation": "1",
            "libelle": "Utilisation de Computer To Plate -CTP-",
            "code_ogr": "21187",
            "position_item": "7",
            "code_type_competence": "2"
        },
        {
            "priorisation": "1",
            "libelle": "Utilisation de Computer To Film -CTF-",
            "code_ogr": "21186",
            "position_item": "8",
            "code_type_competence": "2"
        },
        {
            "priorisation": "1",
            "libelle": "Utilisation de logiciels de gestion de stocks",
            "code_ogr": "21259",
            "position_item": "1",
            "code_type_competence": "2"
        }
    ],
    "parse_appellation": 1,
    "environnement_travail": [
        {
            "priorisation": "1",
            "libelle": "Atelier int\u00e9gr\u00e9",
            "code_ogr": "23716",
            "code_type_section_env": "1"
        },
        {
            "priorisation": "1",
            "libelle": "Entreprise industrielle",
            "code_ogr": "23909",
            "code_type_section_env": "1"
        },
        {
            "priorisation": "1",
            "libelle": "Administration / Services de l'Etat",
            "code_ogr": "23388",
            "code_type_section_env": "2"
        },
        {
            "priorisation": "1",
            "libelle": "Arm\u00e9e",
            "code_ogr": "23401",
            "code_type_section_env": "2"
        },
        {
            "priorisation": "1",
            "libelle": "Communication",
            "code_ogr": "23448",
            "code_type_section_env": "2"
        },
        {
            "priorisation": "1",
            "libelle": "Fa\u00e7onnage/routage",
            "code_ogr": "23497",
            "code_type_section_env": "2"
        },
        {
            "priorisation": "1",
            "libelle": "Gravure industrielle",
            "code_ogr": "38748",
            "code_type_section_env": "2"
        },
        {
            "priorisation": "1",
            "libelle": "Imprimerie de labeur",
            "code_ogr": "23525",
            "code_type_section_env": "2"
        },
        {
            "priorisation": "1",
            "libelle": "Imprimerie de presse",
            "code_ogr": "23526",
            "code_type_section_env": "2"
        },
        {
            "priorisation": "1",
            "libelle": "Imprimerie d'\u00e9dition",
            "code_ogr": "23527",
            "code_type_section_env": "2"
        },
        {
            "priorisation": "1",
            "libelle": "Industrie graphique",
            "code_ogr": "23532",
            "code_type_section_env": "2"
        }
    ],
    "savoir_theorique_et_proceduraux": [
        {
            "priorisation": "1",
            "libelle": "Cha\u00eene graphique",
            "code_ogr": "21702",
            "position_item": "1",
            "code_type_competence": "1"
        },
        {
            "priorisation": "1",
            "libelle": "Colorim\u00e9trie",
            "code_ogr": "21734",
            "position_item": "2",
            "code_type_competence": "1"
        },
        {
            "priorisation": "1",
            "libelle": "Sp\u00e9cificit\u00e9s des supports d'impression",
            "code_ogr": "22718",
            "position_item": "3",
            "code_type_competence": "1"
        },
        {
            "priorisation": "1",
            "libelle": "Techniques d'impression",
            "code_ogr": "23223",
            "position_item": "4",
            "code_type_competence": "1"
        },
        {
            "priorisation": "1",
            "libelle": "Normes qualit\u00e9",
            "code_ogr": "22233",
            "position_item": "5",
            "code_type_competence": "1"
        },
        {
            "priorisation": "1",
            "libelle": "Ordonnancement",
            "code_ogr": "22247",
            "position_item": "6",
            "code_type_competence": "1"
        },
        {
            "priorisation": "1",
            "libelle": "Crit\u00e8res de calibrage de texte",
            "code_ogr": "21763",
            "position_item": "7",
            "code_type_competence": "1"
        },
        {
            "priorisation": "1",
            "libelle": "Techniques de finition/fa\u00e7onnage",
            "code_ogr": "22910",
            "position_item": "8",
            "code_type_competence": "1"
        },
        {
            "priorisation": "1",
            "libelle": "Techniques commerciales",
            "code_ogr": "23012",
            "position_item": "9",
            "code_type_competence": "1"
        },
        {
            "priorisation": "1",
            "libelle": "Techniques de gestion de production",
            "code_ogr": "22922",
            "position_item": "1",
            "code_type_competence": "1"
        },
        {
            "priorisation": "1",
            "libelle": "El\u00e9ments de base en m\u00e9canique g\u00e9n\u00e9rale",
            "code_ogr": "21882",
            "position_item": "1",
            "code_type_competence": "1"
        },
        {
            "priorisation": "1",
            "libelle": "El\u00e9ments de base en \u00e9lectricit\u00e9",
            "code_ogr": "21859",
            "position_item": "2",
            "code_type_competence": "1"
        }
    ],
    "definition": "\nD\u00e9finit et \u00e9labore tout ou partie des donn\u00e9es n\u00e9cessaires \u00e0 la production/fabrication de produits graphiques (devis, dossier de production et de contr\u00f4le, gamme de fabrication, cahier des charges, planning, ordre de fabrication, proc\u00e9dures qualit\u00e9, sous-traitance, ...), en fonction des commandes et des imp\u00e9ratifs de production.\nPeut concevoir ou participer \u00e0 la conception de nouveaux produits (graphiques, multim\u00e9dia, ...) et \u00e9laborer des solutions d'am\u00e9lioration de productivit\u00e9 (techniques, organisationnelles, ...).\nPeut coordonner une \u00e9quipe et diriger un service.\n",
    "intitule": "Intervention technique en industrie graphique",
    "code_ogr": "139",
    "code_rome": "E1308",
    "mobilites_si_evolution": [
        {
            "code_rome_cible": "E1105",
            "libelle_rome_cible": "Coordination d'\u00e9dition"
        },
        {
            "code_rome_cible": "E1205",
            "libelle_rome_cible": "R\u00e9alisation de contenus multim\u00e9dias"
        }
    ]
}